gym_gui_tictactoe/__init__.py
gym_gui_tictactoe/envs/__init__.py
gym_gui_tictactoe/envs/tictactoe_env.py
gym_gui_tictactoe/example/play_game.py
gym_gui_tictactoe/example/play_game_gui.py
gym_gui_tictactoe-0.1.1.dist-info/LICENSE.md
gym_gui_tictactoe-0.1.1.dist-info/METADATA
gym_gui_tictactoe-0.1.1.dist-info/WHEEL
gym_gui_tictactoe-0.1.1.dist-info/top_level.txt
gym_gui_tictactoe-0.1.1.dist-info/RECORD
