Metadata-Version: 2.1
Name: gym_gui_tictactoe
Version: 0.1.1
Summary: An OpenAI gym environment for playing Tic Tac Toe with GUI
Home-page: https://github.com/fauzisho/T3_Env
Author: AI Trafic Project
License: MIT License
Project-URL: Homepage, https://github.com/fauzisho/T3_Env.git
Keywords: tictactoe,gym,pygame
Classifier: License :: OSI Approved :: MIT License
Classifier: Programming Language :: Python
Classifier: Programming Language :: Python :: 3
Requires-Python: >=3.9
License-File: LICENSE.md
Requires-Dist: gym
Requires-Dist: pygame
